[{"content":" Minimalism is not a lack of something. It’s simply the perfect amount of something. — Nicholas Burroughs\n ","href":"/","title":"Home"},{"content":"","href":"/computer-vision/","title":"Computer Vision"},{"content":"Engimo came as combination of two words: \u0026ldquo;engeineering\u0026rdquo; and Minimo.\n","href":"/about-us/","title":"About us"},{"content":"","href":"/authors/achary/","title":"achary"},{"content":"","href":"/authors/","title":"Authors"},{"content":" 1. Bạn đã thật sự hiểu? \n Ảnh 1 Minh họa Object Detection - towardsdatascience \nTheo bạn, Computer Vision (Thị giác máy tính) là gì?\nĐây có vẻ như là một khái niệm mà người không biết thì nghĩ mình biết rất rõ, còn người nghĩ mình không biết thì lại biết rất rõ 🤣. Mình có đi thử hỏi một số bạn thì xem các bạn đó nghĩ Computer Vision là thứ gì trên đời? Mình sẽ gom các câu trả lời thành một số dạng sau đây:\n \u0026ldquo;Computer Vision là Image Processing (xử lý ảnh)\u0026rdquo;\n \u0026ldquo;Computer Vision là Object Detection, Object Recognition\u0026rdquo;\n \u0026ldquo;Computer Vision là dạy cho máy tính hiểu các thông tin thị giác (như ảnh và video) như con người\u0026rdquo;\n \u0026ldquo;Computer Vision là các hệ thống camera sử dụng trí thông minh của máy để giải quyết các công việc của người\u0026rdquo;\n \u0026ldquo;Computer Vision là liên quan tới việc tìm kiếm các quy luật để khai thác thông tin thị giác từ ảnh và video\u0026rdquo;\n  Hmm có vẻ như ai cũng có lý cả đúng không? Theo bạn, theo bạn ai đúng ai sai?\n2. Computer Vision là gì? 2.1 Mỗi bức ảnh là một câu chuyện \n Ảnh 2\nNhìn bức ảnh bạn thấy gì:\n Một tai nạn xe lửa thảm khốc ? Một bức tranh về xưa cũ về tàu hỏa ? Mọi người đang xây dựng hiện trường để đóng phím (có cái thang và dây) ? Một công viên giải trí (theme park) để mọi người chụp hình ?  \n Ảnh 3. Martin Luther King, \u0026ldquo;I Have A Dream\u0026rdquo;   Bạn thấy điều gì ở bức ảnh này? \nNhiều bạn sẽ có cách hiểu hình ảnh trên khác nhau, nhưng các bạn sẽ nhận ra rằng não bạn đã đưa ra câu chuyện (story) khác nhau cho các bức ảnh, và não bạn làm điều này một cách rất tự nhiên bởi ví chúng được sinh ra để làm những việc như thế.\nNhưng \u0026ldquo;story\u0026rdquo; là gì? Tùy thuộc vào việc bạn muốn làm gì với nó! Ví dụ như là:\n Vị trí các vật trong ảnh Cảm xúc của bức ảnh Độ sâu các vật thể trong bức ảnh Hàm ý của bức ảnh\n ..\n  Computer Vision là một lĩnh vực nghiên cứu để khiến máy tính hiểu được các thông tin thị giác tương tự như con người.\nThe goal of computer vision is to write computer programs that can interpret images [3]\n2.2 Định nghĩa \n Ảnh 4. Thị giác trong xe tự hành - informationstrategyrsm \nBây giờ chúng ta sẽ nhìn lại định nghĩa để nhìn nhận lại định một cách chuẩn mực hơn, ở đây có rất nhiều định nghĩa nhưng mình sẽ cố tìm những định nghĩa đáng tin cậy và có tính tổng quát cao . Theo định nghĩa của Dana H. Ballard và Christopher M. Brown trong cuốn sách \u0026ldquo;Computer Vision\u0026rdquo; xuất bản năm 1982:\nComputer vision is an interdisciplinary scientific field that deals with how computers can be made to gain high-level understanding from digital images or videos. From the perspective of engineering, it seeks to automate tasks that the human visual system can do [1]\nNhư vậy là Computer Vision sẽ quan tâm tới việc làm thế nào để khiến máy tính có thể hiểu được các thông tin thị giác như ảnh và videos. Nhiệm vụ chính của Computer Vision là làm cầu nối (bridging) cho khoảng cách từ giữa trí thông minh thị giác của con người với trí thông minh thị giác của máy tính. Ở khía cạnh kĩ thuật thì mục tiêu của Computer Vision là tự động hóa các tác vụ liên quan tới thị giác giống như con người: Detection (nhận dạng), Image Captioning (Nhìn hình kể chuyện), Visual question answering (Hỏi đáp thị giác),..\n3. Vision không phải Image Processing Khác với Image Processing: đầu vào là ảnh và đầu ra là ảnh. Với đầu vào là ảnh, Computer Vision hướng tới đầu ra là .. \u0026ldquo;hiểu\u0026rdquo; bức ảnh. Khi bạn sinh ra, ban đầu bạn sẽ thấy mờ mờ một chút, rồi đột nhiên, bạn thấy và hiểu mọi thứ. Việc nhìn thấy này có vẻ rất đơn giản đối với chúng ta, nhưng với máy tính thì sao?\n3.1. Adelson\u0026rsquo;s Checker-Shadow Effect [5] Checker shadow illusion là một nghiên cứu về ảo ảnh thị giác được công bố bởi Edward H. Edelson, giáo sư về Khoa học Thị giác tại MIT vào năm 1995.\n\n Ảnh 5.  Adelson’s Checker-Shadow Effect\nBức ảnh này gồm một bàn cờ, phần lớn được đổ bóng bằng một khối hình trụ.\nCâu hỏi: Theo bạn, A và B vùng nào tối hơn?\n\u0026hellip; Có vẻ như là B có màu nhạt hơn A.\nOk, giả sử bạn có một cái photometer (thước đo ánh sáng) và bạn áp vào thì sẽ như thế nào:\n\n Ảnh 6.  Adelson’s Checker-Shadow Effect với photometer\nVoila! Photometer sẽ cho bạn thấy rằng A và B đều có số photon như nhau. Như vậy là A và B có màu hoàn toàn giống nhau sao?\nĐúng vậy, bức hình này tạo ra một ảo ảnh thị giác rằng ô vuông A có vẻ như có màu đậm hơn ô vuông B\u0026hellip; hoặc là do não của bạn nghĩ rằng đó là một ô sáng nhưng chả qua nó chỉ được đổ bóng thôi? Từ đó, bạn có thể thấy nguyên nhân tại sao Computer Vision là 1 bài toán khó.\n3.2. Kersten\u0026rsquo;s Shadow Effect Ở ví dụ trước, 2 ô vuông A và B có độ lớn màu (color intensity) hoàn toàn giống nhau, tuy nhiên não của bạn biết chắc chắn ô B là 1 ô màu sáng, chả qua là nó bị đổ bóng thôi. Như vậy, seeing không chỉ đơn thuần là property of measurement (thông số có thể đo lường được), seeing là xây dựng một percept (tri giác) hoặc một description (câu mô tả) về các visual information (thông tin thị giác) mà bạn nhìn thấy[3]. Ở trong não của bạn, điều này diễn ra rất tự nhiên.\nỞ ví dụ này, chúng ta cùng tìm hiểu thêm về một hiện tượng tương tự:\n\n Ảnh 7.  Lifting shadow\n\n Ảnh 8.  Flat-moving shadow\nỞ 2 bức hình này, ta thấy 1 chiếc hộp di chuyển theo 2 hướng khác nhau trên cùng 1 mặt phẳng:\n Một chiếc hộp đi từ trái qua phải và hướng lên trên Một chiếc hộp đi xéo về hướng góc phải của mặt phẳng  Nếu bạn để ý kĩ, hình ảnh 2 chiếc hộp đều nằm ở vị trí giống nhau, chỉ cái bóng là thay đổi. Não chúng ta, với kinh nghiệm hiểu biết về ánh sáng và đổ bóng dày dặn từ cha sinh mẹ đẻ tới giờ, não ta đang giả định rằng có một nguồn sáng phía trên chiếc hộp, và ở hình đầu tiên chiếc hộp được nhấc bổng lên, còn hình bên dưới đi đi với góc phải của mặt phẳng.\nMột lần nữa, seeing không chỉ đơn thuần là property of measurement, mà seeing là understanding.\n3.3. Stereoscope \n Ảnh 9.  Stereoscope -  Wikipedia \nKính lập thể (stereoscope) là một loại thiết bị dùng để xem một cặp ảnh riêng biệt ở dạng lập thể hay dạng ảnh nổi, với nguyên tắc mắt phải và mắt trái nhìn vào cùng một cảnh trên hai ảnh. 6\n\n Ảnh 10.  Một bức hình stereoscope của một phụ nữ đang sử dụng stereoscope -  tumblr \n[4] Mắt chúng ta, nhờ difference (sự khác biệt) giữa 2 bức hình, đã làm cho bạn biết rằng: cô gái đó ngồi phía sau cái bàn và trước một kệ sách.\n3.3. Ambiguity [3] Như vậy, qua 3 ví dụ trên, các bạn có thể tự đặt cho mình một câu hỏi: Phải chăng não chúng ta bằng một cách nào đó đang hoạt động một cách sai lệch? Cái hộp trong hình 7 và hình 8 có lẽ đã không di chuyển theo hướng của chúng ta nghĩ?\nNhưng thật ra, có một ambiguity (sự mơ hồ) về việc chiếc hộp đang di chuyển theo hướng nào, và não của bạn đã viết nên một câu chuyện để giải thích hiện tượng đó. Cuối cùng, sự khác nhau giữa Image Processing và Computer Vision là xây dựng câu chuyện đó.\n4. Computer Vision không dễ 4.1. Images are ambiguous \n Ảnh 11.  Chai coca thật hay giả? -  [4] \n4.2. Objects blend together \n Ảnh 12.  Cái cây..hay là cái gì khác? -  [4] \n4.3. Intra-class variance Kể cả các sự vật cùng loại cũng có intra-class variance lớn (tạm hiểu là khác biệt rất lớn về ngoại hình)\n \n Ảnh 13.  Shape variation (Khác nhau về hình dáng) -  [4] \n\n Ảnh 14.  Occlusion (Bị che khuất) -  [4] \n\n Ảnh 15.  background clutter (ảnh nền lộn xộn) -  [4] \n4.4. Depth ambiguity  \n Ảnh 16.  Người đàn ông đang đứng trước hay kế tháp Pisa? -  [7] \nHoho bằng kinh nghiệm dày dặn của mình bạn đủ thông minh để biết rằng anh này không thể đứng kế tháp Pisa được đúng không? Nhưng còn bức ảnh này thì sao:\n\n Ảnh 17.  Quả cà chua khổng lồ! -  [7] \n4.5. High semantic level \n Ảnh 18.  Ảnh meme -  [7] \nKhoảng cách giữa ảnh meme và ý nghĩa thật sự ẩn chứa trong nó là .. một dải ngân hà. Hiện nay đã có một bài báo [8] của các nghiên cứu sinh Stanford sử dụng Deep Neural Networks để tạo ra cả meme, công nghệ giờ thật là \u0026ldquo;chanh xả\u0026rdquo;!\n\n Ảnh 19.  Ảnh châm biếm -  extracatchy \n5. Tại sao Computer Vision? 6. Các chủ đề tiêu biểu trong Computer Vision { \u0026#34;type\u0026#34;: \u0026#34;line\u0026#34;, \u0026#34;data\u0026#34;: { \u0026#34;labels\u0026#34;: [\u0026#34;One\u0026#34;, \u0026#34;Two\u0026#34;, \u0026#34;Three\u0026#34;, \u0026#34;Four\u0026#34;, \u0026#34;Five\u0026#34;, \u0026#34;Six\u0026#34;], \u0026#34;datasets\u0026#34;: [ { \u0026#34;label\u0026#34;: \u0026#34;# of Votes\u0026#34;, \u0026#34;data\u0026#34;: [12, 19, 3, 5, 2, 3], \u0026#34;backgroundColor\u0026#34;:\u0026#34;transparent\u0026#34;, \u0026#34;borderColor\u0026#34;:\u0026#34;orange\u0026#34; }, { \u0026#34;label\u0026#34;: \u0026#34;Some other set\u0026#34;, \u0026#34;data\u0026#34;: [15, 8, 13, 5, 5, 9], \u0026#34;backgroundColor\u0026#34;:\u0026#34;transparent\u0026#34;, \u0026#34;borderColor\u0026#34;:\u0026#34;#44ccff\u0026#34; } ] } } 7. Tham khảo [1] A Gentle Introduction to Computer Vision - Machine Learning Mastery\n[2] Computer Vision - Wikipedia\n[3] Introduction to Computer Vision - Georgia Tech on Udacity\n[4] CS4670 Cornell\u0026rsquo;s Introduction to Computer Vision\n[5] Checker shadow illusion - Wikipedia\n[6] Stereoscope - wikipedia\n[7] Introduction to Computer Vision - Toyota Technological Institute at Chicago (TTIC)\n[8] Dank Learning: Generating Memes Using DeepNeural Network\n","href":"/computer-vision/computer-vision-la-gi/","title":"Bạn biết gì về Computer Vision?"},{"content":"","href":"/categories/","title":"Categories"},{"content":"","href":"/categories/computer-vision/","title":"computer vision"},{"content":"","href":"/tags/introductory/","title":"introductory"},{"content":"","href":"/authors/muniftanjim/","title":"muniftanjim"},{"content":"","href":"/tags/","title":"Tags"},{"content":"","href":"/tags/vision/","title":"vision"},{"content":"","href":"/tags/engineering/","title":"engineering"},{"content":" Math $$ \\frac{d}{dx}\\left( \\int_{0}^{x} f(u)\\,du\\right)=f(x) $$\nA_n = \\begin{pmatrix} a_1 \u0026amp; a_2 \u0026amp; \\ldots \u0026amp; a_n \\\\\nb_1 \u0026amp; b_2 \u0026amp; \\ldots \u0026amp; b_n \\\\ \\end{pmatrix}\n$$\nGraphviz digraph g { node[shape=\u0026#34;circle\u0026#34; , label=\u0026#34;\u0026#34;, width=0.2, height=0.2] l1[xlabel=\u0026#34;v\\(s\\)\u0026#34;] l21[xlabel=\u0026#34;a\u0026#34;, width=0.1, height=0.1 , style=filled] l22[width=0.1, height=0.3, style=filled] l31[xlabel=\u0026#34;v\\(s\u0026#39;\\)\u0026#34;] l1 -\u0026gt; l21 l1 -\u0026gt; l22 l21 -\u0026gt; l31 [xlabel=\u0026#34;r\u0026#34;] l21 -\u0026gt; l32 l22 -\u0026gt; l33 l22 -\u0026gt; l34 } Waveform { \u0026#34;signal\u0026#34;: [ {\u0026#34;name\u0026#34;: \u0026#34;CLK\u0026#34;, \u0026#34;wave\u0026#34;: \u0026#34;p.....|...\u0026#34;}, {\u0026#34;name\u0026#34;:\u0026#34;DAT\u0026#34;, \u0026#34;wave\u0026#34;:\u0026#34;x.345x|=.x\u0026#34;, \u0026#34;data\u0026#34;:[\u0026#34;A\u0026#34;,\u0026#34;B\u0026#34;,\u0026#34;C\u0026#34;,\u0026#34;D\u0026#34;]}, {\u0026#34;name\u0026#34;: \u0026#34;REQ\u0026#34;, \u0026#34;wave\u0026#34;: \u0026#34;0.1..0|1.0\u0026#34;}, {}, {\u0026#34;name\u0026#34;: \u0026#34;ACK\u0026#34;, \u0026#34;wave\u0026#34;: \u0026#34;1.....|01.\u0026#34;} ]} Chart { \u0026#34;type\u0026#34;: \u0026#34;line\u0026#34;, \u0026#34;data\u0026#34;: { \u0026#34;labels\u0026#34;: [\u0026#34;One\u0026#34;, \u0026#34;Two\u0026#34;, \u0026#34;Three\u0026#34;, \u0026#34;Four\u0026#34;, \u0026#34;Five\u0026#34;, \u0026#34;Six\u0026#34;], \u0026#34;datasets\u0026#34;: [ { \u0026#34;label\u0026#34;: \u0026#34;# of Votes\u0026#34;, \u0026#34;data\u0026#34;: [12, 19, 3, 5, 2, 3] } ] } } MSC Andrew-\u0026gt;China: Says Hello Note right of China: China thinks\\nabout it China--\u0026gt;Andrew: How are you? Andrew-\u0026gt;\u0026gt;China: I am good thanks! Flowcharts st=\u0026gt;start: Start:\u0026gt;http://www.google.com[blank] e=\u0026gt;end:\u0026gt;http://www.google.com op1=\u0026gt;operation: My Operation sub1=\u0026gt;subroutine: My Subroutine cond=\u0026gt;condition: Yes or No?:\u0026gt;http://www.google.com io=\u0026gt;inputoutput: catch something... para=\u0026gt;parallel: parallel tasks st-\u0026gt;op1-\u0026gt;cond cond(yes)-\u0026gt;io-\u0026gt;e cond(no)-\u0026gt;para para(path1, bottom)-\u0026gt;sub1(right)-\u0026gt;op1 para(path2, top)-\u0026gt;op1 Deprecated pages This page has been marked as deprecated. ","href":"/features-summary/","title":"Features Summary"},{"content":"","href":"/page/","title":"Pages"},{"content":"","href":"/tags/config/","title":"Configuration"},{"content":"","href":"/tags/og/","title":"Opengraph"},{"content":"","href":"/search/","title":"Search"},{"content":"","href":"/series/","title":"Series"}]
